log_to_loki/__init__.py
log_to_loki/loki_handler.py
log_to_loki-0.1.1.dist-info/licenses/LICENSE
log_to_loki-0.1.1.dist-info/METADATA
log_to_loki-0.1.1.dist-info/WHEEL
log_to_loki-0.1.1.dist-info/top_level.txt
log_to_loki-0.1.1.dist-info/RECORD
